disc/__init__.py
disc/__main__.py
disc/model.py
disc/evaluation/__init__.py
disc/evaluation/evaluation.py
disc/utils/__init__.py
disc/utils/data_preparation.py
disc/utils/generator.py
disc/utils/utility.py
disc-1.1.6.dist-info/LICENSE
disc-1.1.6.dist-info/METADATA
disc-1.1.6.dist-info/WHEEL
disc-1.1.6.dist-info/entry_points.txt
disc-1.1.6.dist-info/top_level.txt
disc-1.1.6.dist-info/RECORD
