Metadata-Version: 2.1
Name: disc
Version: 1.1.6
Summary: A highly scalable and accurate inference of gene expression and structure for single-cell transcriptomes using semi-supervised deep learning.
Home-page: https://github.com/iyhaoo/DISC
Author: Zhongshan Ophthalmic Centre (ZOC), Sun Yat-sen University (SYSU)
Author-email: 904469382@qq.com
License: Apache License 2.0
Platform: UNKNOWN
Classifier: Programming Language :: Python :: 3.6
Classifier: License :: OSI Approved :: Apache Software License
Classifier: Topic :: Scientific/Engineering :: Artificial Intelligence
Requires-Python: >=3.6
Requires-Dist: numpy (>=1.14.0)
Requires-Dist: pandas (>=0.21.0)
Requires-Dist: tensorflow (<2.0.0,>=1.13.1)
Requires-Dist: h5py (>=2.9.0matplotlib>=3.0.0)
